lpdraw/__init__.py
lpdraw/draw.py
lpdraw-0.0.1.1.dist-info/LICENSE
lpdraw-0.0.1.1.dist-info/METADATA
lpdraw-0.0.1.1.dist-info/WHEEL
lpdraw-0.0.1.1.dist-info/top_level.txt
lpdraw-0.0.1.1.dist-info/RECORD
